denver/__init__.py
denver/denver.py
denver-0.0.2.dist-info/LICENSE
denver-0.0.2.dist-info/METADATA
denver-0.0.2.dist-info/WHEEL
denver-0.0.2.dist-info/entry_points.txt
denver-0.0.2.dist-info/top_level.txt
denver-0.0.2.dist-info/RECORD
