Metadata-Version: 2.1
Name: denver
Version: 0.0.2
Summary: A secret environment management
Home-page: https://git.vptech.eu/ylamouroux/denver
Author: Yoann Lamouroux
Author-email: ylamouroux@vente-privee.com
License: UNKNOWN
Platform: UNKNOWN
Classifier: Development Status :: 2 - Pre-Alpha
Classifier: Programming Language :: Python :: 3
Classifier: License :: OSI Approved :: MIT License
Classifier: Operating System :: OS Independent
Classifier: Environment :: Console
Classifier: Operating System :: POSIX
Requires-Python: >=3.6
Requires-Dist: click
